MANIFEST.in
README.rst
setup.py
django_ipfilter.egg-info/PKG-INFO
django_ipfilter.egg-info/SOURCES.txt
django_ipfilter.egg-info/dependency_links.txt
django_ipfilter.egg-info/top_level.txt
django_ipfilter.egg-info/zip-safe
ipfilter/__init__.py
ipfilter/admin.py
ipfilter/middleware.py
ipfilter/models.py
ipfilter/signals.py