Metadata-Version: 1.0
Name: django-ipfilter
Version: 0.1-dev
Summary: A django application to filter ip addresses in views.
Home-page: http://github.com/powellc/django-ipfilter/
Author: Colin Powell
Author-email: colin@onecardinal.com
License: UNKNOWN
Platform: UNKNOWN
Classifier: Development Status :: 4 - Beta
Classifier: Environment :: Web Environment
Classifier: Framework :: Django
Classifier: Intended Audience :: Developers
Classifier: License :: OSI Approved :: BSD License
Classifier: Operating System :: OS Independent
Classifier: Programming Language :: Python
Classifier: Topic :: Utilities
